<BackupInst xmlns="http://www.microsoft.com/GroupPolicy/GPOOperations/Manifest"><GPOGuid><![CDATA[{A5A78566-CF0F-4819-B851-5E99B0938BC3}]]></GPOGuid><GPODomain><![CDATA[SBPA.org]]></GPODomain><GPODomainGuid><![CDATA[{cd48f7f5-318e-41af-9aa7-48990dad913b}]]></GPODomainGuid><GPODomainController><![CDATA[WIN-H53JMO7OAE8.SBPA.org]]></GPODomainController><BackupTime><![CDATA[2018-08-20T14:03:38]]></BackupTime><ID><![CDATA[{C16791A2-AC1E-42F3-87C3-3913C3A6C948}]]></ID><Comment><![CDATA[]]></Comment><GPODisplayName><![CDATA[Windows 10 1709 L1 Services]]></GPODisplayName></BackupInst>
